aifactory/__init__.py
aifactory/api.py
aifactory/demo.py
aifactory/grade.py
aifactory/make_zip.py
aifactory/score.py
aifactory/train.py
aifactory-2.0.0.dist-info/METADATA
aifactory-2.0.0.dist-info/WHEEL
aifactory-2.0.0.dist-info/top_level.txt
aifactory-2.0.0.dist-info/RECORD
