Metadata-Version: 2.1
Name: aifactory
Version: 2.0.0
Summary: aifactory-cli
Home-page: https://aifactory.space
Author: aifactory
Author-email: contact@aifactory.page
License: MIT
Requires-Python: >=3
Requires-Dist: pipreqs
Requires-Dist: ipynbname
Requires-Dist: gdown
Requires-Dist: requests
Requires-Dist: IPython
